chdf/__init__.py
chdf-0.0.1.dist-info/LICENSE
chdf-0.0.1.dist-info/METADATA
chdf-0.0.1.dist-info/WHEEL
chdf-0.0.1.dist-info/top_level.txt
chdf-0.0.1.dist-info/RECORD
