Metadata-Version: 2.1
Name: chdf
Version: 0.0.1
Summary: chdf
Home-page: https://github.com/pypa/sampleproject
Author: josenight
Author-email: author@example.com
License: UNKNOWN
Platform: UNKNOWN
Classifier: Programming Language :: Python :: 3
Classifier: License :: OSI Approved :: MIT License
Classifier: Operating System :: OS Independent
Requires-Python: >=3.6
License-File: LICENSE
